petljapub/__init__.py
petljapub/code_parser.py
petljapub/competition.py
petljapub/compilation.py
petljapub/config.py
petljapub/configure_compilers.py
petljapub/cpp_parser.py
petljapub/default_checker.py
petljapub/fix_latex.py
petljapub/fix_latex_try.py
petljapub/javascript.py
petljapub/logger.py
petljapub/main.py
petljapub/markdown_magic_comments.py
petljapub/md_content_processor.py
petljapub/md_util.py
petljapub/messages.py
petljapub/petlja_account.py
petljapub/plot_times.py
petljapub/publication_repository.py
petljapub/publication_visitor.py
petljapub/publication_visitor_html.py
petljapub/publication_visitor_petlja.py
petljapub/publication_visitor_testing.py
petljapub/publication_visitor_tex.py
petljapub/py_parser.py
petljapub/serialization.py
petljapub/source_code_magic_comments.py
petljapub/task.py
petljapub/task_repository.py
petljapub/task_visitor.py
petljapub/task_visitor_html.py
petljapub/tasks.py
petljapub/translit.py
petljapub/util.py
petljapub/yaml_specification.py
petljapub/yaml_specification_visitor_runtime.py
petljapub/yaml_specification_visitor_stats.py
petljapub/data/compile-cs.sh
petljapub/data/template.yaml
petljapub/data/_task_template/task-tgen.cpp
petljapub/data/_task_template/task.cpp
petljapub/data/_task_template/task.cs
petljapub/data/_task_template/task.py
petljapub/data/_task_template/en/task-sol.md
petljapub/data/_task_template/en/task-st.md
petljapub/data/_task_template/sr-Cyrl/task-sol.md
petljapub/data/_task_template/sr-Cyrl/task-st.md
petljapub/data/_task_template/sr-Latn/task-sol.md
petljapub/data/_task_template/sr-Latn/task-st.md
petljapub/data/html/pandoc.css
petljapub/data/md/header.md
petljapub/data/tex/default.latex
petljapub/data/tgen/tgen-geom.hpp
petljapub/data/tgen/tgen-graph.hpp
petljapub/data/tgen/tgen.hpp
petljapub/data/tgen/tgen.py
petljapub/data/tgen/tgen.py~
petljapub-2.1.15.dist-info/LICENCE
petljapub-2.1.15.dist-info/METADATA
petljapub-2.1.15.dist-info/WHEEL
petljapub-2.1.15.dist-info/entry_points.txt
petljapub-2.1.15.dist-info/top_level.txt
petljapub-2.1.15.dist-info/RECORD
