Metadata-Version: 2.1
Name: petljapub
Version: 2.1.15
Summary: Petlja publishing system
Home-page: https://github.com/pypa/petljapub
Author: Filip Maric, Petlja
Author-email: filip.maric@petlja.org
Project-URL: Bug Tracker, https://github.com/pypa/petljapub/issues
Classifier: Programming Language :: Python :: 3
Classifier: License :: OSI Approved :: MIT License
Classifier: Operating System :: OS Independent
Requires-Python: >=3.7
License-File: LICENCE
Requires-Dist: invoke
Requires-Dist: requests
Requires-Dist: pyyaml
Requires-Dist: pypandoc
Requires-Dist: pandoc-xnos
Requires-Dist: pandoc-fignos
Requires-Dist: pandoc-eqnos
Requires-Dist: pandoc-tablenos
Requires-Dist: appdirs
Requires-Dist: matplotlib>=3.4
Requires-Dist: petlja-api
